holded_dataflow-0.1.7.dist-info/METADATA
holded_dataflow-0.1.7.dist-info/WHEEL
holded_dataflow-0.1.7.dist-info/license_files/LICENSE
holded_dataflow/py.typed
holded_dataflow/__init__.pyi
holded_dataflow/parse.py
holded_dataflow/filter.py
holded_dataflow/holded_dataflow.cpython-312-x86_64-linux-gnu.so
holded_dataflow-0.1.7.dist-info/RECORD
