Metadata-Version: 2.3
Name: holded-dataflow
Version: 0.1.7
Classifier: Programming Language :: Python :: 3
Classifier: Programming Language :: Rust
Classifier: License :: OSI Approved :: MIT License
Classifier: License :: OSI Approved :: Apache Software License
License-File: LICENSE
Summary: Core logic of ingestion pipeline
Keywords: rust,python,bindings
Author-email: Yohan Valencia <yohan.vt@gmail.com>
License: Apache-2.0
Requires-Python: >=3.8
